{
  "project_info": {
    "project_number": "338256298268",
    "project_id": "tts-library",
    "storage_bucket": "tts-library.appspot.com"
  },
  "client": [
    {
      "client_info": {
        "mobilesdk_app_id": "1:338256298268:android:62f0a3b351ff9001e13ad9",
        "android_client_info": {
          "package_name": "com.ttslibrary.android"
        }
      },
      "oauth_client": [
        {
          "client_id": "338256298268-0hh85tuo88llovihnss7esdndfrci10h.apps.googleusercontent.com",
          "client_type": 3
        }
      ],
      "api_key": [
        {
          "current_key": "AIzaSyATHMP6z20zOs81YhQH3ananK2OIpWvcCs"
        }
      ],
      "services": {
        "appinvite_service": {
          "other_platform_oauth_client": [
            {
              "client_id": "338256298268-0hh85tuo88llovihnss7esdndfrci10h.apps.googleusercontent.com",
              "client_type": 3
            },
            {
              "client_id": "338256298268-50rgker5jkt0i3ugggj21b5764ts50nk.apps.googleusercontent.com",
              "client_type": 2,
              "ios_info": {
                "bundle_id": "com.ttslibrary.ios"
              }
            }
          ]
        }
      }
    }
  ],
  "configuration_version": "1"
}